span/LICENSE
span/README_ANDROID.txt
span/__init__.py
span/__main__.py
span/params.py
span/readme_span.txt
span/span_imports.py
span/span_main.py
span/user_manual_SPAN_7.4.pdf
span/version_histories.txt
span/FreeSimpleGUI_local/FreeSimpleGUI.py
span/FreeSimpleGUI_local/__init__.py
span/FreeSimpleGUI_local/license.txt
span/example_files/index_list_sample.txt
span/example_files/ngc5806_bins.dat
span/example_files/nir_indices_gasparri2021_angstrom.dat
span/example_files/sample_templates.txt
span/example_files/xshooter_vis_sample_list_spectra.dat
span/example_files/results/NGC5320_populations.dat
span/example_files/results/ew_data.dat
span/example_files/results/sigma_coeff.dat
span/example_files/results/sigma_data.dat
span/example_files/results/sigma_data_ngc5806_bins_new.dat
span/example_files/spectra/NGC0636_VIS_dopcor.fits
span/example_files/spectra/NGC0897_VIS_dopcor.fits
span/example_files/spectra/NGC1600_VIS_dopcor.fits
span/example_files/spectra/NGC3379_VIS_dopcor.fits
span/example_files/spectra/NGC3423_VIS_dopcor.fits
span/example_files/spectra/NGC5806_image.fits
span/example_files/spectra/NGC5806/line0.fits
span/example_files/spectra/NGC5806/line1.fits
span/example_files/spectra/NGC5806/line10.fits
span/example_files/spectra/NGC5806/line11.fits
span/example_files/spectra/NGC5806/line12.fits
span/example_files/spectra/NGC5806/line13.fits
span/example_files/spectra/NGC5806/line14.fits
span/example_files/spectra/NGC5806/line15.fits
span/example_files/spectra/NGC5806/line16.fits
span/example_files/spectra/NGC5806/line17.fits
span/example_files/spectra/NGC5806/line18.fits
span/example_files/spectra/NGC5806/line19.fits
span/example_files/spectra/NGC5806/line2.fits
span/example_files/spectra/NGC5806/line20.fits
span/example_files/spectra/NGC5806/line21.fits
span/example_files/spectra/NGC5806/line22.fits
span/example_files/spectra/NGC5806/line23.fits
span/example_files/spectra/NGC5806/line24.fits
span/example_files/spectra/NGC5806/line25.fits
span_gui-7.4.1.dist-info/METADATA
span_gui-7.4.1.dist-info/WHEEL
span_gui-7.4.1.dist-info/entry_points.txt
span_gui-7.4.1.dist-info/top_level.txt
span_gui-7.4.1.dist-info/RECORD
