Metadata-Version: 2.4
Name: span-gui
Version: 7.4.1
Summary: GUI program for the manipulation and analysis of astronomical spectra in the optical and NIR wavelength ranges.
Author-email: Daniele Gasparri <daniele.gasparri@gmail.com>
License: SPAN License
Project-URL: Homepage, https://github.com/danielegasparri/span-gui
Project-URL: Issue Tracker, https://github.com/danielegasparri/span-gui/issues
Keywords: spectral analysis,galaxies,spectral manipulation,linestrength analysis,astronomy,spectral fitting,spectroscopy,data analysis,kinematics,stellar populations
Classifier: Programming Language :: Python :: 3
Classifier: License :: Free for non-commercial use
Classifier: Operating System :: OS Independent
Classifier: Topic :: Scientific/Engineering :: Astronomy
Classifier: Intended Audience :: Science/Research
Requires-Python: >=3.10
Requires-Dist: numpy<=2.2.6,>=1.24.1
Requires-Dist: astropy<=7.1.0,>=6.1.0
Requires-Dist: pandas>=2.2.3
Requires-Dist: matplotlib>=3.10.0
Requires-Dist: scipy<=1.16.0,>=1.15.0
Requires-Dist: scikit-image>=0.25.2
Requires-Dist: PyWavelets<=1.8.0,>=1.7.0
Requires-Dist: joblib<=1.4.2,>=1.3.2
Requires-Dist: scikit-learn<=1.7.0,>=1.3.0
Requires-Dist: ppxf>=9.4.1
Requires-Dist: vorbin<3.2.0,>=3.1.7
Requires-Dist: certifi>=2025.1.31
Requires-Dist: emcee>=3.1.6
Requires-Dist: powerbin>=1.1.9
